Workbook

Sheet AUTHORS_CORREGIDO_FINAL (1)
A1: author_name | B1: keywords | C1: Columna1 | D1: Columna2 | E1: Columna3
A2: Juan Claudio Escobar | B2: Chile; Educación Superior; Coronavirus; Buena práctica | C2: [Chile; Educación Superior; Coronavirus; Buena práctica] | D2: Chile; Educación Superior; Coronavirus; Buena práctica; | E2: =_xlfn.XLOOKUP(A2, Autores_correos!B:B, Autores_correos!A:A,"No encontrado") -> No encontrado
A3: Marcelo Gómez Cobos | B3: Liderazgo; Gestión; Personalidad; Empoderamiento; Habilidades | C3: [Liderazgo; Gestión; Personalidad; Empoderamiento; Habilidades] | D3: Liderazgo; Gestión; Personalidad; Empoderamiento; Habilidades; | E3: =_xlfn.XLOOKUP(A3, Autores_correos!B:B, Autores_correos!A:A,"No encontrado") -> No encontrado
A4: Juan Manuel Martín García | B4: Formación; Gestión; Gobernanza; Universidad; Plan estratégico | C4: [Formación; Gestión; Gobernanza; Universidad; Plan estratégico] | D4: Formación; Gestión; Gobernanza; Universidad; Plan estratégico; | E4: =_xlfn.XLOOKUP(A4, Autores_correos!B:B, Autores_correos!A:A,"No encontrado") -> No encontrado
A5: Ascensión Palomares Ruiz | B5: Liderazgo; Universidad; Investigación; Innovación; Emprendimiento; Género | C5: [Liderazgo; Universidad; Investigación; Innovación; Emprendimiento; Género] | D5: Liderazgo; Universidad; Investigación; Innovación; Emprendimiento; Género; | E5: =_xlfn.XLOOKUP(A5, Autores_correos!B:B, Autores_correos!A:A,"No encontrado") -> No encontrado
A6: Isabel Vera Trallero | B6: Liderazgo; Gestión; Competencias técnicas; Competencias transversales | C6: [Liderazgo; Gestión; Competencias técnicas; Competencias transversales] | D6: Liderazgo; Gestión; Competencias técnicas; Competencias transversales; | E6: =_xlfn.XLOOKUP(A6, Autores_correos!B:B, Autores_correos!A:A,"No encontrado") -> No encontrado
A7: Javier Oliver Villarroya | B7: Liderazgo; Gestión; Educación Universitaria; Aprendizaje centrado en el estudiante | C7: [Liderazgo; Gestión; Educación Universitaria; Aprendizaje centrado en el estudiante] | D7: Liderazgo; Gestión; Educación Universitaria; Aprendizaje centrado en el estudiante; | E7: =_xlfn.XLOOKUP(A7, Autores_correos!B:B, Autores_correos!A:A,"No encontrado") -> No encontrado
A8: Elizabeth Guilarte Barinaga | B8: Educación de calidad; Procesos sustantivos; Educación superior; Proyectos I+D; ODS | C8: [Educación de calidad; Procesos sustantivos; Educación superior; Proyectos I+D; ODS] | D8: Educación de calidad; Procesos sustantivos; Educación superior; Proyectos I+D; ODS; | E8: =_xlfn.XLOOKUP(A8, Autores_correos!B:B, Autores_correos!A:A,"No encontrado") -> No encontrado
A9: Marcia Esther Noda Hernández | B9: Educación de calidad; Procesos sustantivos; Educación superior; Proyectos I+D; ODS | C9: [Educación de calidad; Procesos sustantivos; Educación superior; Proyectos I+D; ODS] | D9: Educación de calidad; Procesos sustantivos; Educación superior; Proyectos I+D; ODS; | E9: =_xlfn.XLOOKUP(A9, Autores_correos!B:B, Autores_correos!A:A,"No encontrado") -> No encontrado
A10: Isabel Ortiz Marcos | B10: Liderazgo; Instituciones de Educación Superior; Gestión del cambio | C10: [Liderazgo; Instituciones de Educación Superior; Gestión del cambio] | D10: Liderazgo; Instituciones de Educación Superior; Gestión del cambio; | E10: =_xlfn.XLOOKUP(A10, Autores_correos!B:B, Autores_correos!A:A,"No encontrado") -> No encontrado
A11: Raquel Castillo de Oyagüe | B11: Calidad; Universidades; Rankings; Reputación | C11: [Calidad; Universidades; Rankings; Reputación] | D11: Calidad; Universidades; Rankings; Reputación; | E11: =_xlfn.XLOOKUP(A11, Autores_correos!B:B, Autores_correos!A:A,"No encontrado") -> No encontrado
A12: Miguel Angel Sastre Castillo | B12: Calidad; Universidades; Rankings; Reputación | C12: [Calidad; Universidades; Rankings; Reputación] | D12: Calidad; Universidades; Rankings; Reputación; | E12: =_xlfn.XLOOKUP(A12, Autores_correos!B:B, Autores_correos!A:A,"No encontrado") -> No encontrado
A13: Agustín Daniel Gómez Fuentes | B13: Investigadores; Psicología; Disciplina; Ciencia | C13: [Investigadores; Psicología; Disciplina; Ciencia] | D13: Investigadores; Psicología; Disciplina; Ciencia; | E13: =_xlfn.XLOOKUP(A13, Autores_correos!B:B, Autores_correos!A:A,"No encontrado") -> No encontrado
... A31434: Koshka Duff | B31434: violencia; liberalismo; ideología; Black live matter; Walter Benjamin | C31434: [violencia; liberalismo; ideología; Black live matter; Walter Benjamin] | D31434: violencia; liberalismo; ideología; Black live matter; Walter Benjamin; | E31434: =_xlfn.XLOOKUP(A31434, Autores_correos!B:B, Autores_correos!A:A,"No encontrado") -> No encontrado

Sheet Autores_correos
A1: Column1 | B1: Column2
A2: email | B2: name
A3: 0000-0002-esther.garcia@uleam.edu.ec | B3: María Esther García Montes
A4: 0009061e@umich.mx | B4: Dulce Celeste Arriaga Trejo
A5: 014417500@ulsaoaxaca.edu.mx | B5: Diego Escudero-Sanchez
A6: 0490060x@umich.mx | B6: EUSTORGIO GONZÁLEZ TORRES
A7: 0618551x@umich.mx | B7: Miguel Ángel Ramírez Hernández
A8: 07473585916@udesc.edu.br | B8: Guilherme Da Conceição De Lima
A9: 0942457755@aitec.edu.ec | B9: Juan José Piguave Balladares
A10: 100079379@alumnos.uc3m.es | B10: Jesús Martín Matallana
A11: 1002220182@unajma.edu.pe | B11: Oliver León Manchi
A12: 100435813@alumnos.uc3m.es | B12: Reyler Rodríguez Chávez
... A16798: zyn@servidor.unam.mx | B16798: Patricia Kurczyn Villalobos

Sheet Hoja1
